es_query_gen/__init__.py
es_query_gen/builder.py
es_query_gen/models.py
es_query_gen/parser.py
es_query_gen/py.typed
es_query_gen/es_utils/connection.py
es_query_gen/es_utils/schema_validator.py
es_query_gen-1.10.0.dist-info/METADATA
es_query_gen-1.10.0.dist-info/WHEEL
es_query_gen-1.10.0.dist-info/RECORD
