Metadata-Version: 2.4
Name: es-query-gen
Version: 1.10.0
Summary: Library to build complex ES queries from simple Python dictionaries using typed Pydantic models.
Project-URL: Homepage, https://github.com/goyal15rajat/es-query-builder
Author-email: "rajat.goyal" <goyal.rajat15@gmail.com>
Keywords: dsl,elasticsearch,pydantic,query-builder,search,typing
Classifier: Development Status :: 3 - Alpha
Classifier: Framework :: Pydantic :: 2
Classifier: Intended Audience :: Developers
Classifier: Intended Audience :: Information Technology
Classifier: License :: OSI Approved :: MIT License
Classifier: Programming Language :: Python :: 3
Classifier: Programming Language :: Python :: 3.10
Classifier: Programming Language :: Python :: 3.11
Classifier: Programming Language :: Python :: 3.12
Classifier: Topic :: Internet :: WWW/HTTP :: Indexing/Search
Classifier: Topic :: Software Development :: Libraries :: Python Modules
Classifier: Topic :: Text Processing :: Indexing
Classifier: Typing :: Typed
Requires-Python: >=3.10
Requires-Dist: aiohttp>=3.13.2
Requires-Dist: elasticsearch[async]<9.0.0,>=7.0.0
Requires-Dist: pydantic>=2.12.5
Requires-Dist: pytest-asyncio>=1.3.0
Requires-Dist: pytest-cov>=7.0.0
Requires-Dist: pytest>=9.0.2
Requires-Dist: python-dateutil>=2.9.0.post0
